examples/__init__.py
examples/error.py
examples/failed_deps.py
examples/success.py
parproc/__init__.py
parproc/par.py
parproc/state.py
parproc/term.py
parproc-0.3.2.dist-info/licenses/LICENSE.txt
parproc-0.3.2.dist-info/METADATA
parproc-0.3.2.dist-info/WHEEL
parproc-0.3.2.dist-info/top_level.txt
parproc-0.3.2.dist-info/RECORD
